depx/__init__.py
depx/__main__.py
depx/cli.py
depx/config.py
depx/core/__init__.py
depx/core/analyzer.py
depx/core/cleaner.py
depx/core/dependency_manager.py
depx/core/exporter.py
depx/core/global_scanner.py
depx/core/scanner.py
depx/core/package_managers/__init__.py
depx/core/package_managers/base.py
depx/core/package_managers/cargo.py
depx/core/package_managers/npm.py
depx/core/package_managers/pip.py
depx/core/package_managers/yarn.py
depx/i18n/__init__.py
depx/i18n/i18n_manager.py
depx/parsers/__init__.py
depx/parsers/base.py
depx/parsers/csharp.py
depx/parsers/go.py
depx/parsers/java.py
depx/parsers/nodejs.py
depx/parsers/php.py
depx/parsers/python.py
depx/parsers/rust.py
depx/utils/__init__.py
depx/utils/display.py
depx/utils/error_handling.py
depx/utils/file_utils.py
depx/utils/language_info.py
depx/utils/performance.py
depx/utils/toml_utils.py
depx-0.9.0.dist-info/licenses/LICENSE
depx-0.9.0.dist-info/METADATA
depx-0.9.0.dist-info/WHEEL
depx-0.9.0.dist-info/entry_points.txt
depx-0.9.0.dist-info/top_level.txt
depx-0.9.0.dist-info/RECORD
