Metadata-Version: 2.4
Name: depx
Version: 0.9.0
Summary: 本地多语言依赖统一管理器
Home-page: https://github.com/yourusername/depx
Author: Depx Team
Author-email: Depx Team <depx@example.com>
Maintainer-email: Depx Team <depx@example.com>
License: MIT
Project-URL: Homepage, https://github.com/yourusername/depx
Project-URL: Repository, https://github.com/yourusername/depx
Project-URL: Documentation, https://github.com/yourusername/depx#readme
Project-URL: Bug Tracker, https://github.com/yourusername/depx/issues
Keywords: dependency,package-manager,nodejs,python,analysis,cleanup,global-packages
Classifier: Development Status :: 3 - Alpha
Classifier: Intended Audience :: Developers
Classifier: License :: OSI Approved :: MIT License
Classifier: Operating System :: OS Independent
Classifier: Programming Language :: Python :: 3
Classifier: Programming Language :: Python :: 3.8
Classifier: Programming Language :: Python :: 3.9
Classifier: Programming Language :: Python :: 3.10
Classifier: Programming Language :: Python :: 3.11
Classifier: Programming Language :: Python :: 3.12
Classifier: Topic :: Software Development :: Libraries :: Python Modules
Classifier: Topic :: System :: Systems Administration
Classifier: Topic :: Utilities
Requires-Python: >=3.8
License-File: LICENSE
Requires-Dist: click>=8.0.0
Requires-Dist: rich>=13.0.0
Requires-Dist: pyyaml>=6.0.0
Provides-Extra: dev
Requires-Dist: pytest>=7.0.0; extra == "dev"
Requires-Dist: pytest-cov>=4.0.0; extra == "dev"
Dynamic: author
Dynamic: home-page
Dynamic: license-file
Dynamic: requires-python
